shxd/__init__.py
shxd/__main__.py
shxd/main.py
shxd/parser.py
shxd/utils.py
shxd/commands/__init__.py
shxd/commands/native/__init__.py
shxd/commands/native/clone.py
shxd/commands/native/ping.py
shxd-0.1.dist-info/LICENSE
shxd-0.1.dist-info/METADATA
shxd-0.1.dist-info/WHEEL
shxd-0.1.dist-info/entry_points.txt
shxd-0.1.dist-info/top_level.txt
shxd-0.1.dist-info/RECORD
