Metadata-Version: 2.1
Name: shxd
Version: 0.1
Summary: A CLI to extend shell functionality for developers.
Home-page: https://github.com/luiisp/shxd
Author: Pedro Luis Dias
Author-email: luisp.diias@gmail.com
Classifier: Programming Language :: Python :: 3
Classifier: Programming Language :: Python :: 3.6
Classifier: Programming Language :: Python :: 3.7
Classifier: Programming Language :: Python :: 3.8
Classifier: Programming Language :: Python :: 3.9
Classifier: Programming Language :: Python :: 3.10
Classifier: License :: OSI Approved :: MIT License
Classifier: Operating System :: OS Independent
Requires-Python: >=3.6
License-File: LICENSE
Requires-Dist: requests
Requires-Dist: pygments
Requires-Dist: colorama
